baseq/__init__.py
baseq/cmd.py
baseq/docs.py
baseq/setting.py
baseq/bam/__init__.py
baseq/bam/bamtype.py
baseq/bam/cigar.py
baseq/bam/cmd.py
baseq/bam/doc.py
baseq/bam/stats.py
baseq/bam/depth/__init__.py
baseq/bam/depth/depth.py
baseq/bam/depth/plot.py
baseq/bam/qc/__init__.py
baseq/bam/qc/complexity.py
baseq/bam/qc/duplicate.py
baseq/bed/__init__.py
baseq/bed/cmd.py
baseq/bed/docs.py
baseq/bed/intersect.py
baseq/bed/merge.py
baseq/bed/sort.py
baseq/cnv/__init__.py
baseq/cnv/bincount.py
baseq/cnv/docs.py
baseq/cnv/normalize.py
baseq/cnv/results.py
baseq/cnv/segment.py
baseq/cnv/plots/__init__.py
baseq/cnv/plots/genome.py
baseq/cnv/plots/heatmap.py
baseq/cnv/plots/region.py
baseq/drops/__init__.py
baseq/drops/aggregate.py
baseq/drops/bam_parser.py
baseq/drops/cmd.py
baseq/drops/run_star.py
baseq/drops/tag_gene.py
baseq/drops/whitelist.py
baseq/drops/apa/UTR.py
baseq/drops/apa/__init__.py
baseq/drops/apa/cmd.py
baseq/drops/apa/docs.py
baseq/drops/apa/genes.py
baseq/drops/apa/samples.py
baseq/drops/apa/scaner.py
baseq/drops/barcode/__init__.py
baseq/drops/barcode/count.py
baseq/drops/barcode/split.py
baseq/drops/barcode/split_fast.py
baseq/drops/barcode/stats.py
baseq/drops/cellranger/__init__.py
baseq/drops/cellranger/cluster.py
baseq/drops/cellranger/cmd.py
baseq/drops/cellranger/docs.py
baseq/fastq/__init__.py
baseq/fastq/docs.py
baseq/fastq/filter_reads.py
baseq/fastq/quality.py
baseq/fastq/sample_file.py
baseq/fastq/split_barcode.py
baseq/mgt/__init__.py
baseq/mgt/check.py
baseq/mgt/command.py
baseq/mgt/config.py
baseq/mgt/history.py
baseq/mgt/resource.py
baseq/rna/__init__.py
baseq/rna/cmd.py
baseq/rna/docs.py
baseq/rna/filetype.py
baseq/rna/hisat.py
baseq/rna/salmon.py
baseq/rna/star.py
baseq/rna/qc/__init__.py
baseq/rna/qc/corrheatmap.py
baseq/rna/qc/exp_table.py
baseq/rna/qc/markers.py
baseq/rna/qc/pca.py
baseq/rna/qc/precision.py
baseq/rna/qc/scatterplot.py
baseq-0.1.2.dist-info/DESCRIPTION.rst
baseq-0.1.2.dist-info/METADATA
baseq-0.1.2.dist-info/RECORD
baseq-0.1.2.dist-info/WHEEL
baseq-0.1.2.dist-info/entry_points.txt
baseq-0.1.2.dist-info/metadata.json
baseq-0.1.2.dist-info/top_level.txt
